[
    {
      "station no": 101,
      "user id": 1,
      "user name": "Alice",
      "shift no": "Morning",
      "date": "2024-12-06",
      "time": "08:00",
      "programme no": "P001",
      "cycle": 12,
      "angle": 45,
      "weld current": 300,
      "spot current": 50,
      "force": 200,
      "weld count": 5,
      "job": "Weld A",
      "error": "Overheat",
      "errorCode": "101"
    },
    {
      "station no": 102,
      "user id": 2,
      "user name": "Bob",
      "shift no": "Afternoon",
      "date": "2024-12-06",
      "time": "13:00",
      "programme no": "P002",
      "cycle": 15,
      "angle": 60,
      "weld current": 310,
      "spot current": 55,
      "force": 210,
      "weld count": 6,
      "job": "Weld B",
      "error": "Voltage Drop",
      "errorCode": "102"
    },
    {
      "station no": 103,
      "user id": 3,
      "user name": "Charlie",
      "shift no": "Night",
      "date": "2024-12-06",
      "time": "22:00",
      "programme no": "P003",
      "cycle": 10,
      "angle": 30,
      "weld current": 290,
      "spot current": 45,
      "force": 190,
      "weld count": 4,
      "job": "Weld C",
      "error": "Alignment Issue",
      "errorCode": "103"
    },
    {
      "station no": 104,
      "user id": 4,
      "user name": "Diana",
      "shift no": "Morning",
      "date": "2024-12-06",
      "time": "09:00",
      "programme no": "P004",
      "cycle": 14,
      "angle": 50,
      "weld current": 320,
      "spot current": 60,
      "force": 220,
      "weld count": 7,
      "job": "Weld D",
      "error": "",
      "errorCode": "0"
    },
    {
      "station no": 105,
      "user id": 5,
      "user name": "Eve",
      "shift no": "Afternoon",
      "date": "2024-12-06",
      "time": "14:30",
      "programme no": "P005",
      "cycle": 16,
      "angle": 70,
      "weld current": 330,
      "spot current": 65,
      "force": 230,
      "weld count": 8,
      "job": "Weld E",
      "error": "Overload",
      "errorCode": "104"
    }
  ]
  